{"cameraMode":{"drawMode":0,"name":"Shaded","section":"Shading Mode"},"sceneLighting":false,"audioPlay":false,"sceneViewState":{"m_AlwaysRefresh":false,"showFog":true,"showSkybox":false,"showFlares":true,"showImageEffects":true,"showParticleSystems":true,"showVisualEffectGraphs":true,"m_FxEnabled":true},"in2DMode":false,"pivot":{"x":-17.358642578125,"y":2.584406852722168,"z":10.43007755279541},"rotation":{"x":-0.20439940690994264,"y":-0.6677693128585815,"z":0.1984773427248001,"w":-0.6876890659332275},"size":7.835277557373047,"orthographic":false}